moretunes/spotify/__init__.py
moretunes/spotify/enhanced.py
moretunes/spotify/exceptions.py
moretunes/spotify/utils.py
moretunes/spotify/web.py
moretunes/spotify/tokens/__init__.py
moretunes/spotify/tokens/anon.py
moretunes/spotify/tokens/extract.py
moretunes/spotify/tokens/web_user.py
moretunes_spotify-0.4.3rc15.dev1.dist-info/LICENSE
moretunes_spotify-0.4.3rc15.dev1.dist-info/METADATA
moretunes_spotify-0.4.3rc15.dev1.dist-info/WHEEL
moretunes_spotify-0.4.3rc15.dev1.dist-info/top_level.txt
moretunes_spotify-0.4.3rc15.dev1.dist-info/RECORD
