Metadata-Version: 2.1
Name: moretunes-spotify
Version: 0.4.3rc15.dev1
Summary: python wrapper for the Spotify based on Tekore with extensions for the WebAPI
Author-email: jcbirdwell <jcbirdwell@gmail.com>
License: MIT License
Classifier: Programming Language :: Python :: 3
Classifier: License :: OSI Approved :: MIT License
Classifier: Development Status :: 3 - Alpha
Requires-Python: >=3.12
License-File: LICENSE
Requires-Dist: httpx
Requires-Dist: requests
Requires-Dist: pydantic
Requires-Dist: tekore ~=5.4.0
